jupyterlab_mol_visualizer/__init__.py
jupyterlab_mol_visualizer/_version.py
jupyterlab_mol_visualizer-1.0.0.data/data/share/jupyter/labextensions/jupyterlab_mol_visualizer/build_log.json
jupyterlab_mol_visualizer-1.0.0.data/data/share/jupyter/labextensions/jupyterlab_mol_visualizer/package.json
jupyterlab_mol_visualizer-1.0.0.data/data/share/jupyter/labextensions/jupyterlab_mol_visualizer/static/lib_index_js-webpack_sharing_consume_default_react-dom.b2a2cb12294f2d6064ec.js
jupyterlab_mol_visualizer-1.0.0.data/data/share/jupyter/labextensions/jupyterlab_mol_visualizer/static/lib_index_js-webpack_sharing_consume_default_react-dom.b2a2cb12294f2d6064ec.js.map
jupyterlab_mol_visualizer-1.0.0.data/data/share/jupyter/labextensions/jupyterlab_mol_visualizer/static/remoteEntry.a5fc84cc4ad1463ebeed.js
jupyterlab_mol_visualizer-1.0.0.data/data/share/jupyter/labextensions/jupyterlab_mol_visualizer/static/remoteEntry.a5fc84cc4ad1463ebeed.js.map
jupyterlab_mol_visualizer-1.0.0.data/data/share/jupyter/labextensions/jupyterlab_mol_visualizer/static/style.js
jupyterlab_mol_visualizer-1.0.0.data/data/share/jupyter/labextensions/jupyterlab_mol_visualizer/static/style_index_js.9c456f4b769bc4caa8b8.js
jupyterlab_mol_visualizer-1.0.0.data/data/share/jupyter/labextensions/jupyterlab_mol_visualizer/static/style_index_js.9c456f4b769bc4caa8b8.js.map
jupyterlab_mol_visualizer-1.0.0.data/data/share/jupyter/labextensions/jupyterlab_mol_visualizer/static/vendors-node_modules_material-ui_core_esm_Box_Box_js-node_modules_material-ui_core_esm_CssBas-bb75a9.5e130e634246dc4e7abe.js
jupyterlab_mol_visualizer-1.0.0.data/data/share/jupyter/labextensions/jupyterlab_mol_visualizer/static/vendors-node_modules_material-ui_core_esm_Box_Box_js-node_modules_material-ui_core_esm_CssBas-bb75a9.5e130e634246dc4e7abe.js.map
jupyterlab_mol_visualizer-1.0.0.data/data/share/jupyter/labextensions/jupyterlab_mol_visualizer/install.json
jupyterlab_mol_visualizer-1.0.0.dist-info/METADATA
jupyterlab_mol_visualizer-1.0.0.dist-info/WHEEL
jupyterlab_mol_visualizer-1.0.0.dist-info/licenses/LICENSE
jupyterlab_mol_visualizer-1.0.0.dist-info/RECORD
