Metadata-Version: 2.3
Name: jupyterlab_mol_visualizer
Version: 1.0.0
Dynamic: Keywords
Summary: A JupyterLab launcher extension to view the molecular orbitals.
Project-URL: Homepage, https://github.com/osscar-org/jupyterlab-mol-visualizer
Project-URL: Bug Tracker, https://github.com/osscar-org/jupyterlab-mol-visualizer/issues
Project-URL: Repository, https://github.com/osscar-org/jupyterlab-mol-visualizer.git
Author-email: Dou Du <dou.du@icloud.com>
License: BSD 3-Clause License
License-File: LICENSE
Classifier: Framework :: Jupyter
Classifier: Framework :: Jupyter :: JupyterLab
Classifier: Framework :: Jupyter :: JupyterLab :: 4
Classifier: Framework :: Jupyter :: JupyterLab :: Extensions
Classifier: Framework :: Jupyter :: JupyterLab :: Extensions :: Prebuilt
Classifier: License :: OSI Approved :: BSD License
Classifier: Programming Language :: Python
Classifier: Programming Language :: Python :: 3
Classifier: Programming Language :: Python :: 3.8
Classifier: Programming Language :: Python :: 3.9
Classifier: Programming Language :: Python :: 3.10
Classifier: Programming Language :: Python :: 3.11
Requires-Python: >=3.8
